[
  {
    "title": "Important Link",
    "links": [
      {
        "href": "/",
        "label": "Home Page"
      },
      {
        "label": "Register",
        "href": "https://reg2025.igcc-jeddah.com/"
      },
      {
        "href": "/message",
        "label": "Message"
      },
      {
        // "href": "/agenda",
        "href": "/Poster_compressed.pdf",
        "label": "Agenda"
      },
      {
        "href": "/speakers",
        "label": "Speakers"
      },
      {
        "href": "/Moderators",
        "label": "Moderators"
      },
      {
        "href": "/sponsors",
        "label": "Sponsors"
      },
      {
        "href": "/gallery",
        "label": "Gallery"
      }
    ]
  }
]